aperturedb/BBoxDataCSV.py
aperturedb/BlobDataCSV.py
aperturedb/BlobNewestDataCSV.py
aperturedb/Blobs.py
aperturedb/BoundingBoxes.py
aperturedb/CSVParser.py
aperturedb/CSVWriter.py
aperturedb/Clips.py
aperturedb/CommonLibrary.py
aperturedb/Configuration.py
aperturedb/ConnectionDataCSV.py
aperturedb/Connector.py
aperturedb/ConnectorRest.py
aperturedb/Constraints.py
aperturedb/DaskManager.py
aperturedb/DataModels.py
aperturedb/DescriptorDataCSV.py
aperturedb/DescriptorSetDataCSV.py
aperturedb/Descriptors.py
aperturedb/Entities.py
aperturedb/EntityDataCSV.py
aperturedb/EntityUpdateDataCSV.py
aperturedb/ImageDataCSV.py
aperturedb/ImageDownloader.py
aperturedb/Images.py
aperturedb/KaggleData.py
aperturedb/MLCroissant.py
aperturedb/NotebookHelpers.py
aperturedb/Operations.py
aperturedb/ParallelLoader.py
aperturedb/ParallelQuery.py
aperturedb/ParallelQuerySet.py
aperturedb/Parallelizer.py
aperturedb/PolygonDataCSV.py
aperturedb/Polygons.py
aperturedb/PyTorchData.py
aperturedb/PyTorchDataset.py
aperturedb/Query.py
aperturedb/QueryGenerator.py
aperturedb/SPARQL.py
aperturedb/Sort.py
aperturedb/Sources.py
aperturedb/SparseAddingDataCSV.py
aperturedb/Stats.py
aperturedb/Subscriptable.py
aperturedb/TensorFlowData.py
aperturedb/Utils.py
aperturedb/VideoDataCSV.py
aperturedb/VideoDownloader.py
aperturedb/Videos.py
aperturedb/__init__.py
aperturedb/queryMessage.py
aperturedb/queryMessage3_pb2.py
aperturedb/queryMessage4_pb2.py
aperturedb/queryMessage5_pb2.py
aperturedb/types.py
aperturedb/cli/__init__.py
aperturedb/cli/adb.py
aperturedb/cli/configure.py
aperturedb/cli/console.py
aperturedb/cli/ingest.py
aperturedb/cli/keys.py
aperturedb/cli/mount_coco.py
aperturedb/cli/tokens.py
aperturedb/cli/transact.py
aperturedb/cli/utilities.py
aperturedb/transformers/__init__.py
aperturedb/transformers/clip.py
aperturedb/transformers/clip_pytorch_embeddings.py
aperturedb/transformers/common_properties.py
aperturedb/transformers/facenet.py
aperturedb/transformers/facenet_pytorch_embeddings.py
aperturedb-0.4.53.dist-info/licenses/LICENSE
aperturedb-0.4.53.dist-info/METADATA
aperturedb-0.4.53.dist-info/WHEEL
aperturedb-0.4.53.dist-info/entry_points.txt
aperturedb-0.4.53.dist-info/top_level.txt
aperturedb-0.4.53.dist-info/RECORD
