Metadata-Version: 2.4
Name: aperturedb
Version: 0.4.53
Summary: ApertureDB Python SDK
Author-email: ApertureData Engineering <team@aperturedata.io>
License: The MIT License
Project-URL: Homepage, https://github.com/aperture-data/aperturedb-python
Project-URL: Bug Reports, https://github.com/aperture-data/aperturedb-python/issues
Keywords: aperturedb,graph,database,image,video,metadata,search,indexing
Requires-Python: >=3.8
License-File: LICENSE
Requires-Dist: protobuf<6.0.0,>=3.20.3
Requires-Dist: requests
Requires-Dist: boto3
Requires-Dist: numpy<2; python_version < "3.9.0"
Requires-Dist: numpy
Requires-Dist: distributed
Requires-Dist: matplotlib
Requires-Dist: pandas
Requires-Dist: kaggle!=1.6.15
Requires-Dist: google-cloud-storage
Requires-Dist: ipython
Requires-Dist: dask[complete]
Requires-Dist: ipywidgets
Requires-Dist: pydantic>=2.6.0
Requires-Dist: devtools
Requires-Dist: typer
Requires-Dist: opencv-python-headless
Requires-Dist: ipywidgets==8.0.4
Requires-Dist: keepalive-socket==0.0.1
Requires-Dist: graphviz==0.20.2
Requires-Dist: python-dotenv
Provides-Extra: notebook
Requires-Dist: torch; extra == "notebook"
Requires-Dist: torchvision; extra == "notebook"
Requires-Dist: tensorflow; extra == "notebook"
Requires-Dist: facenet-pytorch; extra == "notebook"
Provides-Extra: complete
Requires-Dist: torch; extra == "complete"
Requires-Dist: torchvision; extra == "complete"
Requires-Dist: tensorflow; extra == "complete"
Requires-Dist: facenet-pytorch; extra == "complete"
Provides-Extra: dev
Requires-Dist: torch; extra == "dev"
Requires-Dist: torchvision; extra == "dev"
Requires-Dist: tensorflow; extra == "dev"
Requires-Dist: facenet-pytorch; extra == "dev"
Requires-Dist: coverage; extra == "dev"
Requires-Dist: autopep8; extra == "dev"
Requires-Dist: pre-commit; extra == "dev"
Requires-Dist: pytest; extra == "dev"
Requires-Dist: build; extra == "dev"
Requires-Dist: fuse-python; platform_system == "Linux" and extra == "dev"
Requires-Dist: rdflib; extra == "dev"
Dynamic: license-file
